othdrplot/__init__.py
othdrplot/draw_univariate_sample.py
othdrplot/high_density_region_algorithm.py
othdrplot/karhunen_loeve_dimension_reduction_algorithm.py
othdrplot/process_high_density_region_algorithm.py
othdrplot/data/chute-trajectories.csv
othdrplot/data/gauss-mixture-3D.csv
othdrplot/data/gauss-mixture.csv
othdrplot/data/logistic-trajectories.csv
othdrplot-2.2.dist-info/COPYING
othdrplot-2.2.dist-info/COPYING.LESSER
othdrplot-2.2.dist-info/METADATA
othdrplot-2.2.dist-info/WHEEL
othdrplot-2.2.dist-info/top_level.txt
othdrplot-2.2.dist-info/RECORD
