Metadata-Version: 2.1
Name: othdrplot
Version: 2.2
Summary: High Density Region plot
Home-page: https://github.com/mbaudin47/othdrplot
Author: Michaël Baudin and Pamphile Roy
Author-email: michael.baudin@gmail.com
License: LGPL
Keywords: graphics
Platform: UNKNOWN
Classifier: Development Status :: 5 - Production/Stable
Classifier: Environment :: Console
Classifier: License :: OSI Approved :: GNU Lesser General Public License v3 (LGPLv3)
Classifier: Intended Audience :: Science/Research
Classifier: Intended Audience :: Developers
Classifier: Natural Language :: English
Classifier: Operating System :: Unix
Classifier: Programming Language :: Python :: 2
Classifier: Programming Language :: Python :: 3
Classifier: Topic :: Documentation :: Sphinx
Classifier: Topic :: Software Development
Classifier: Topic :: Scientific/Engineering
License-File: COPYING
License-File: COPYING.LESSER
Requires-Dist: numpy
Requires-Dist: matplotlib
Requires-Dist: openturns (>=1.16)
